dmgbuild/__init__.py
dmgbuild/__main__.py
dmgbuild/badge.py
dmgbuild/colors.py
dmgbuild/core.py
dmgbuild/licensing.py
dmgbuild/resources/builtin-arrow.tiff
dmgbuild-1.6.6.dist-info/licenses/LICENSE
dmgbuild-1.6.6.dist-info/METADATA
dmgbuild-1.6.6.dist-info/WHEEL
dmgbuild-1.6.6.dist-info/entry_points.txt
dmgbuild-1.6.6.dist-info/top_level.txt
dmgbuild-1.6.6.dist-info/RECORD
