Metadata-Version: 2.4
Name: dmgbuild
Version: 1.6.6
Summary: macOS command line utility to build disk images
Author-email: Alastair Houghton <alastair@alastairs-place.net>
Maintainer-email: Russell Keith-Magee <russell@keith-magee.com>
License-Expression: MIT
Project-URL: Documentation, https://dmgbuild.readthedocs.io/en/latest/
Project-URL: Homepage, https://github.com/dmgbuild/dmgbuild
Project-URL: Tracker, https://github.com/dmgbuild/dmgbuild/issues
Project-URL: Source, https://github.com/dmgbuild/dmgbuild
Keywords: dmg
Classifier: Development Status :: 5 - Production/Stable
Classifier: Programming Language :: Python :: 3
Classifier: Programming Language :: Python :: 3.10
Classifier: Programming Language :: Python :: 3.11
Classifier: Programming Language :: Python :: 3.12
Classifier: Programming Language :: Python :: 3.13
Classifier: Programming Language :: Python :: 3.14
Classifier: Programming Language :: Python :: 3.15
Classifier: Programming Language :: Python :: 3 :: Only
Classifier: Topic :: Desktop Environment
Classifier: Topic :: Software Development :: Libraries :: Python Modules
Requires-Python: >=3.10
License-File: LICENSE
Requires-Dist: ds_store>=1.1.0
Requires-Dist: mac_alias>=2.0.1
Provides-Extra: badge-icons
Requires-Dist: pyobjc-framework-Quartz>=3.0.4; extra == "badge-icons"
Dynamic: license-file
